discordifyText/__init__.py
discordifyText/__main__.py
discordifyText/discordifyText.py
discordifytext-0.1.5.dist-info/LICENSE
discordifytext-0.1.5.dist-info/METADATA
discordifytext-0.1.5.dist-info/WHEEL
discordifytext-0.1.5.dist-info/entry_points.txt
discordifytext-0.1.5.dist-info/top_level.txt
discordifytext-0.1.5.dist-info/RECORD
