Metadata-Version: 2.2
Name: discordifyText
Version: 0.1.5
Summary: A package that transforms your sentences into various 'discord lingo', developed with pipenv, built with build using setuptools, uploaded to PyPI using twine, and distributed via pip.
Author-email: Harini Buddaluru <hb2657@nyu.edu>, Franyel Diaz Rodriguez <fd2190@nyu.edu>, Suhan Suresh <suuhansuresh@gmail.com>, Jackson Chen <ymchen0125@gmail.com>
License:                     GNU GENERAL PUBLIC LICENSE
Project-URL: Homepage, https://github.com/software-students-spring2025/3-python-package-minesweepers
Project-URL: Repository, https://github.com/software-students-spring2025/3-python-package-minesweepers.git
Project-URL: Bug Tracker, https://github.com/software-students-spring2025/3-python-package-minesweepers/issues
Keywords: python,package,build,tutorial
Classifier: Programming Language :: Python :: 3
Classifier: Intended Audience :: Education
Classifier: License :: OSI Approved :: GNU General Public License v3 (GPLv3)
Classifier: Operating System :: OS Independent
Requires-Python: >=3.7
License-File: LICENSE
Provides-Extra: dev
Requires-Dist: pytest; extra == "dev"
